MANIFEST.in
README.rst
setup.cfg
setup.py
dcmt/__init__.py
dcmt/exceptions.py
dcmt/functions.py
dcmt/version.py
dcmt.egg-info/PKG-INFO
dcmt.egg-info/SOURCES.txt
dcmt.egg-info/dependency_links.txt
dcmt.egg-info/requires.txt
dcmt.egg-info/top_level.txt
doc/source/conf.py
doc/source/index.rst
src/dcmt/CHANGELOG
src/dcmt/README
src/dcmt/README.jp
src/dcmt/VERSION
src/dcmt/include/dc.h
src/dcmt/lib/Makefile
src/dcmt/lib/check32.c
src/dcmt/lib/dci.h
src/dcmt/lib/eqdeg.c
src/dcmt/lib/genmtrand.c
src/dcmt/lib/init.c
src/dcmt/lib/mt19937.c
src/dcmt/lib/mt19937.h
src/dcmt/lib/prescr.c
src/dcmt/lib/seive.c
src/wrapper/wrapper.c
test/test.py