Metadata-Version: 1.0
Name: dcmt
Version: 0.6.1-2
Summary: Dynamical creation of Mersenne twisters
Home-page: http://github.com/Manticore/python-dcmt
Author: Bogdan Opanchuk
Author-email: mantihor@gmail.com
License: UNKNOWN
Platform: UNKNOWN
Classifier: Development Status :: 4 - Beta
Classifier: Intended Audience :: Developers
Classifier: License :: OSI Approved :: MIT License
Classifier: Operating System :: OS Independent
Classifier: Programming Language :: Python :: 2
Classifier: Topic :: Scientific/Engineering :: Mathematics
